dslectures/__init__.py
dslectures/_nbdev.py
dslectures/core.py
dslectures/image_downloader.py
dslectures/structured.py
dslectures-0.0.15.dist-info/LICENSE
dslectures-0.0.15.dist-info/METADATA
dslectures-0.0.15.dist-info/WHEEL
dslectures-0.0.15.dist-info/entry_points.txt
dslectures-0.0.15.dist-info/top_level.txt
dslectures-0.0.15.dist-info/RECORD
