Metadata-Version: 2.1
Name: dslectures
Version: 0.0.15
Summary: Course materials for introductory data science
Home-page: https://github.com/lewtun/dslectures
Author: Lewis Tunstall
Author-email: lewis.c.tunstall@gmail.com
License: GNU Affero General Public License v3
Keywords: datascience,machinelearning
Platform: UNKNOWN
Classifier: Development Status :: 3 - Alpha
Classifier: Intended Audience :: Developers
Classifier: License :: OSI Approved :: GNU Affero General Public License v3 
Classifier: Natural Language :: English
Classifier: Programming Language :: Python :: 3.6
Classifier: Programming Language :: Python :: 3.7
Classifier: Programming Language :: Python :: 3.8
Requires-Python: >=3.6
Requires-Dist: scikit-learn
Requires-Dist: pandas
Requires-Dist: numpy
Requires-Dist: seaborn
Requires-Dist: black
Requires-Dist: nltk
Requires-Dist: tqdm
Requires-Dist: wget
Requires-Dist: nbdev
Requires-Dist: sklearn-pandas
Requires-Dist: graphviz
Requires-Dist: giotto-tda
Requires-Dist: selenium
Requires-Dist: beautifulsoup4
